zdppy_excel/__init__.py
zdppy_excel/_constants.py
zdppy_excel/cell/__init__.py
zdppy_excel/cell/_writer.py
zdppy_excel/cell/cell.py
zdppy_excel/cell/read_only.py
zdppy_excel/cell/rich_text.py
zdppy_excel/cell/text.py
zdppy_excel/chart/_3d.py
zdppy_excel/chart/__init__.py
zdppy_excel/chart/_chart.py
zdppy_excel/chart/area_chart.py
zdppy_excel/chart/axis.py
zdppy_excel/chart/bar_chart.py
zdppy_excel/chart/bubble_chart.py
zdppy_excel/chart/chartspace.py
zdppy_excel/chart/data_source.py
zdppy_excel/chart/descriptors.py
zdppy_excel/chart/error_bar.py
zdppy_excel/chart/label.py
zdppy_excel/chart/layout.py
zdppy_excel/chart/legend.py
zdppy_excel/chart/line_chart.py
zdppy_excel/chart/marker.py
zdppy_excel/chart/picture.py
zdppy_excel/chart/pie_chart.py
zdppy_excel/chart/pivot.py
zdppy_excel/chart/plotarea.py
zdppy_excel/chart/print_settings.py
zdppy_excel/chart/radar_chart.py
zdppy_excel/chart/reader.py
zdppy_excel/chart/reference.py
zdppy_excel/chart/scatter_chart.py
zdppy_excel/chart/series.py
zdppy_excel/chart/series_factory.py
zdppy_excel/chart/shapes.py
zdppy_excel/chart/stock_chart.py
zdppy_excel/chart/surface_chart.py
zdppy_excel/chart/text.py
zdppy_excel/chart/title.py
zdppy_excel/chart/trendline.py
zdppy_excel/chart/updown_bars.py
zdppy_excel/chartsheet/__init__.py
zdppy_excel/chartsheet/chartsheet.py
zdppy_excel/chartsheet/custom.py
zdppy_excel/chartsheet/properties.py
zdppy_excel/chartsheet/protection.py
zdppy_excel/chartsheet/publish.py
zdppy_excel/chartsheet/relation.py
zdppy_excel/chartsheet/views.py
zdppy_excel/comments/__init__.py
zdppy_excel/comments/author.py
zdppy_excel/comments/comment_sheet.py
zdppy_excel/comments/comments.py
zdppy_excel/comments/shape_writer.py
zdppy_excel/compat/__init__.py
zdppy_excel/compat/abc.py
zdppy_excel/compat/numbers.py
zdppy_excel/compat/product.py
zdppy_excel/compat/singleton.py
zdppy_excel/compat/strings.py
zdppy_excel/descriptors/__init__.py
zdppy_excel/descriptors/base.py
zdppy_excel/descriptors/excel.py
zdppy_excel-0.1.0.dist-info/LICENSE
zdppy_excel-0.1.0.dist-info/METADATA
zdppy_excel-0.1.0.dist-info/WHEEL
zdppy_excel-0.1.0.dist-info/RECORD
