Metadata-Version: 2.1
Name: zdppy-excel
Version: 0.1.0
Summary: Python处理Excel的专属工具库
Author: zhangdapeng520
Author-email: 1156956636@qq.com
Requires-Python: >=3.11,<4.0
Classifier: Programming Language :: Python :: 3
Classifier: Programming Language :: Python :: 3.11
Classifier: Programming Language :: Python :: 3.12
